setup.py
ExcelRateToolbox/Cashflows.py
ExcelRateToolbox/__init__.py
ExcelRateToolbox/test_Cashflows.py
ExcelRateToolbox.egg-info/PKG-INFO
ExcelRateToolbox.egg-info/SOURCES.txt
ExcelRateToolbox.egg-info/dependency_links.txt
ExcelRateToolbox.egg-info/not-zip-safe
ExcelRateToolbox.egg-info/top_level.txt