Metadata-Version: 1.0
Name: ExcelRateToolbox
Version: 0.1
Summary: Python method emulating the Excel RATE() Function but with improved convergence
Home-page: UNKNOWN
Author: Michael J Swickrath
Author-email: michael.swickrath@gmail.com
License: UNKNOWN
Platform: UNKNOWN
